README.md
setup.py
wms_downloader/__init__.py
wms_downloader/download.py
wms_downloader.egg-info/PKG-INFO
wms_downloader.egg-info/SOURCES.txt
wms_downloader.egg-info/dependency_links.txt
wms_downloader.egg-info/entry_points.txt
wms_downloader.egg-info/requires.txt
wms_downloader.egg-info/top_level.txt