Metadata-Version: 1.2
Name: wms-downloader
Version: 1.1.0
Summary: Downloads large geo TIFF files from a WMS service.
Home-page: https://github.com/codeforberlin/wms-downloader
Author: Jochen Klar
Author-email: jochenklar@gmail.com
Maintainer: Jochen Klar
Maintainer-email: jochenklar@gmail.com
License: MIT
Platform: UNKNOWN
